CHANGES.txt
COPYING
LICENSE
MANIFEST.in
README.txt
VERSION.txt
setup.py
krpctools/__init__.py
krpctools/utils.py
krpctools/version.py
krpctools.egg-info/PKG-INFO
krpctools.egg-info/SOURCES.txt
krpctools.egg-info/dependency_links.txt
krpctools.egg-info/entry_points.txt
krpctools.egg-info/requires.txt
krpctools.egg-info/top_level.txt
krpctools/bin/Google.Protobuf.dll
krpctools/bin/KRPC.Core.dll
krpctools/bin/KRPC.Core.xml
krpctools/bin/KRPC.IO.Ports.dll
krpctools/bin/NDesk.Options.dll
krpctools/bin/Newtonsoft.Json.dll
krpctools/bin/ServiceDefinitions.exe
krpctools/bin/System.Core.dll
krpctools/bin/System.IO.dll
krpctools/bin/System.Runtime.dll
krpctools/bin/System.Xml.dll
krpctools/bin/System.dll
krpctools/bin/TestServer-0.5.4.zip
krpctools/bin/mscorlib.dll
krpctools/clientgen/__init__.py
krpctools/clientgen/cnano.py
krpctools/clientgen/cnano.tmpl
krpctools/clientgen/cpp.py
krpctools/clientgen/cpp.tmpl
krpctools/clientgen/csharp.py
krpctools/clientgen/csharp.tmpl
krpctools/clientgen/docparser.py
krpctools/clientgen/generator.py
krpctools/clientgen/java.py
krpctools/clientgen/java.tmpl
krpctools/clientgen/python.py
krpctools/clientgen/python.tmpl
krpctools/docgen/__init__.py
krpctools/docgen/cnano.py
krpctools/docgen/cnano.tmpl
krpctools/docgen/cpp.py
krpctools/docgen/cpp.tmpl
krpctools/docgen/csharp.py
krpctools/docgen/csharp.tmpl
krpctools/docgen/docgen.py
krpctools/docgen/domain.py
krpctools/docgen/extensions.py
krpctools/docgen/java.py
krpctools/docgen/java.tmpl
krpctools/docgen/lua.py
krpctools/docgen/lua.tmpl
krpctools/docgen/nodes.py
krpctools/docgen/python.py
krpctools/docgen/python.tmpl
krpctools/docgen/utils.py
krpctools/lang/__init__.py
krpctools/lang/cnano.py
krpctools/lang/cpp.py
krpctools/lang/csharp.py
krpctools/lang/java.py
krpctools/lang/language.py
krpctools/lang/lua.py
krpctools/lang/python.py
krpctools/servicedefs/__init__.py
krpctools/test/Empty.json
krpctools/test/TestService.json
krpctools/test/__init__.py
krpctools/test/clientgen-Empty-cnano.txt
krpctools/test/clientgen-Empty-cpp.txt
krpctools/test/clientgen-Empty-csharp.txt
krpctools/test/clientgen-Empty-java.txt
krpctools/test/clientgen-TestService-cnano.txt
