Metadata-Version: 2.1
Name: krpctools
Version: 0.5.4
Summary: Development tools and scripts for kRPC.
Home-page: https://krpc.github.io/krpc
Author: djungelorm
Author-email: djungelorm@users.noreply.github.com
License: GNU GPL v3
Platform: UNKNOWN
Classifier: Development Status :: 5 - Production/Stable
Classifier: Intended Audience :: End Users/Desktop
Classifier: License :: OSI Approved :: GNU General Public License v3 (GPLv3)
Classifier: Natural Language :: English
Classifier: Programming Language :: Python :: 3
Classifier: Operating System :: Microsoft :: Windows
Classifier: Operating System :: Unix
Classifier: Topic :: Communications
Classifier: Topic :: Games/Entertainment :: Simulation
Classifier: Topic :: Internet
Requires-Python: >=3.4
License-File: LICENSE
License-File: COPYING
